kobo_highlights_extractor/__init__.py
kobo_highlights_extractor/extractor.py
kobo_highlights_extractor-0.1.0.dist-info/LICENSE
kobo_highlights_extractor-0.1.0.dist-info/METADATA
kobo_highlights_extractor-0.1.0.dist-info/WHEEL
kobo_highlights_extractor-0.1.0.dist-info/top_level.txt
kobo_highlights_extractor-0.1.0.dist-info/RECORD
