Metadata-Version: 2.1
Name: kobo-highlights-extractor
Version: 0.1.0
Summary: A package to extract highlights from kobo books
Author-email: Toni Miquel Llull <tonimiquel.llull@gmail.com>
Project-URL: Homepage, https://gitlab.com/tmllull/kobo-highlights-extractor
Project-URL: Bug Tracker, https://gitlab.com/tmllull/kobo-highlights-extractor/issues
Project-URL: Documentation, https://kobo-highlights-extractor.readthedocs.io
Keywords: kobo,ereader
Classifier: License :: OSI Approved :: GNU General Public License v3 (GPLv3)
Classifier: Programming Language :: Python :: 3
Requires-Python: >=3.11
License-File: LICENSE
Requires-Dist: Jinja2 ==3.1.3
